{"assets":{"40ABB0E16578D459C3A659ABC0D082A6":{"type":"texture","index":0,"assetRequest":{"type":"slide","state":"contents","slide":"none"},"url":{"native":"assets\/AD5CF6D7-0911-41BE-8AFE-C5A5B1F92F66.pdf"},"width":1920,"height":1080},"86717BA614C16FD3315B4104A4C976B6":{"type":"texture","index":1,"assetRequest":{"type":"slide","state":"contents","slide":"none"},"url":{"native":"assets\/AD5CF6D7-0911-41BE-8AFE-C5A5B1F92F66.pdf"},"width":1920,"height":1080}},"events":[{"effects":[{"beginTime":0,"baseLayer":{"animations":[],"initialState":{"affineTransform":[1,0,0,1,0,0],"masksToBounds":false,"rotation":0,"scale":1,"position":{"pointX":960,"pointY":540},"width":1920,"sublayerTransform":[1,0,0,0,0,1,0,0,0,0,1,0,0,0,0,1],"contentsRect":{"y":0,"x":0,"width":1,"height":1},"opacity":1,"edgeAntialiasingMask":251658240,"height":1080,"hidden":false,"anchorPoint":{"pointX":0.5,"pointY":0.5}},"objectID":"0","layers":[{"animations":[],"initialState":{"affineTransform":[1,0,0,1,0,0],"masksToBounds":false,"rotation":0,"scale":1,"position":{"pointX":960,"pointY":540},"width":1920,"sublayerTransform":[1,0,0,0,0,1,0,0,0,0,1,-0.00035007912466775983,0,0,0,1],"contentsRect":{"y":0,"x":0,"width":1,"height":1},"opacity":1,"edgeAntialiasingMask":251658240,"height":1080,"hidden":false,"anchorPoint":{"pointX":0.5,"pointY":0.5}},"layers":[{"animations":[{"timeOffset":0,"values":[{"scalar":0},{"scalar":0},{"scalar":1},{"scalar":1}],"beginTime":0,"repeatCount":0,"fillMode":"both","property":"opacity","autoreverses":false,"duration":0.70000000000000007,"keyTimes":[0,0.5,0.501,1]}],"layers":[],"texturedRectangle":{"isBackgroundTexture":false,"singleTextureOpacity":1,"textureType":0,"textBaseline":0,"textXHeight":0,"isVerticalText":false},"initialState":{"affineTransform":[1,0,0,1,0,0],"masksToBounds":false,"rotation":0,"scale":1,"position":{"pointX":960,"pointY":540},"width":1920,"sublayerTransform":[1,0,0,0,0,1,0,0,0,0,1,0,0,0,0,1],"contentsRect":{"y":0,"x":0,"width":1,"height":1},"opacity":1,"edgeAntialiasingMask":0,"height":1080,"hidden":false,"anchorPoint":{"pointX":0.5,"pointY":0.5}},"texture":"86717BA614C16FD3315B4104A4C976B6"},{"animations":[{"timeOffset":0,"values":[{"scalar":1},{"scalar":1},{"scalar":0},{"scalar":0}],"beginTime":0,"repeatCount":0,"fillMode":"both","property":"opacity","autoreverses":false,"duration":0.70000000000000007,"keyTimes":[0,0.5,0.501,1]}],"layers":[],"texturedRectangle":{"isBackgroundTexture":false,"singleTextureOpacity":1,"textureType":0,"textBaseline":0,"textXHeight":0,"isVerticalText":false},"initialState":{"affineTransform":[1,0,0,1,0,0],"masksToBounds":false,"rotation":0,"scale":1,"position":{"pointX":960,"pointY":540},"width":1920,"sublayerTransform":[1,0,0,0,0,1,0,0,0,0,1,0,0,0,0,1],"contentsRect":{"y":0,"x":0,"width":1,"height":1},"opacity":1,"edgeAntialiasingMask":0,"height":1080,"hidden":false,"anchorPoint":{"pointX":0.5,"pointY":0.5}},"texture":"40ABB0E16578D459C3A659ABC0D082A6"},{"animations":[{"timeOffset":0,"beginTime":0,"repeatCount":0,"animations":[{"timeOffset":0,"timingFunctions":[{"timingFunction":"EaseIn"},{"timingFunction":"EaseOut"}],"beginTime":0,"values":[{"scalar":0},{"scalar":1},{"scalar":0}],"repeatCount":0,"fillMode":"removed","property":"opacity","autoreverses":false,"duration":0.70000000000000007,"keyTimes":[0,0.5,1]},{"timeOffset":0,"from":{"scalar":false},"beginTime":0,"repeatCount":0,"fillMode":"removed","property":"hidden","autoreverses":false,"duration":0.70000000000000007,"to":{"scalar":false}}],"fillMode":"both","autoreverses":false,"duration":0.70000000000000007}],"initialState":{"affineTransform":[1,0,0,1,0,0],"scale":1,"rotation":0,"masksToBounds":false,"position":{"pointX":960,"pointY":540},"backgroundColor":[0,0,0,1],"width":1920,"sublayerTransform":[1,0,0,0,0,1,0,0,0,0,1,0,0,0,0,1],"contentsRect":{"y":0,"x":0,"width":1,"height":1},"opacity":1,"edgeAntialiasingMask":251658240,"height":1080,"hidden":true,"anchorPoint":{"pointX":0.5,"pointY":0.5}},"layers":[]}]}]},"effects":[],"duration":0.70000000000000007,"type":"transition","name":"com.apple.iWork.Keynote.BLTFadeThruColor","objectID":"0"}],"automaticPlay":false,"hyperlinks":[],"accessibility":[{"text":"pasted-image.pdf","targetRectangle":{"y":-170.37374877929688,"x":-1315.956298828125,"width":1920,"height":1286.4000244140625}},{"text":"Migrated to a new cloud based, auto-scaling and load-balanced architecture with a high performant client-side application","targetRectangle":{"y":444.30949783325195,"x":898.03891734135141,"width":908.50000166565178,"height":501.59999370574951}},{"text":"WE LEARNED FROM OUR GROWTH","targetRectangle":{"y":116.31567193550057,"x":154.71132408287082,"width":385.31999999999988,"height":223.60000205039978}}],"baseLayer":{"animations":[],"initialState":{"affineTransform":[1,0,0,1,0,0],"masksToBounds":false,"rotation":0,"scale":1,"position":{"pointX":960,"pointY":540},"width":1920,"sublayerTransform":[1,0,0,0,0,1,0,0,0,0,1,0,0,0,0,1],"contentsRect":{"y":0,"x":0,"width":1,"height":1},"opacity":1,"edgeAntialiasingMask":251658240,"height":1080,"hidden":false,"anchorPoint":{"pointX":0.5,"pointY":0.5}},"objectID":"0","layers":[{"animations":[],"initialState":{"affineTransform":[1,0,0,1,0,0],"masksToBounds":false,"rotation":0,"scale":1,"position":{"pointX":960,"pointY":540},"width":1920,"sublayerTransform":[1,0,0,0,0,1,0,0,0,0,1,-0.00035007912466775983,0,0,0,1],"contentsRect":{"y":0,"x":0,"width":1,"height":1},"opacity":1,"edgeAntialiasingMask":251658240,"height":1080,"hidden":false,"anchorPoint":{"pointX":0.5,"pointY":0.5}},"layers":[{"animations":[],"layers":[],"texturedRectangle":{"isBackgroundTexture":false,"singleTextureOpacity":1,"textureType":0,"textBaseline":0,"textXHeight":0,"isVerticalText":false},"initialState":{"affineTransform":[1,0,0,1,0,0],"masksToBounds":false,"rotation":0,"scale":1,"position":{"pointX":960,"pointY":540},"width":1920,"sublayerTransform":[1,0,0,0,0,1,0,0,0,0,1,0,0,0,0,1],"contentsRect":{"y":0,"x":0,"width":1,"height":1},"opacity":1,"edgeAntialiasingMask":0,"height":1080,"hidden":false,"anchorPoint":{"pointX":0.5,"pointY":0.5}},"texture":"40ABB0E16578D459C3A659ABC0D082A6"}]}]}}]}